{"operationid":"GetNotifyQRCode","tag":"wwopencrmlogic","summary":"获取「学校通知」二维码","path":"https://qyapi.weixin.qq.com/cgi-bin/externalcontact/get_subscribe_qr_code","method":"GET","permission":"学校需要使用[“家校沟通”secret](#90001/90143/92313/开始开发)或配置到“[可调用应用](#90001/90143/92313/开始开发)”列表中的自建应用secret所获取的accesstoken来调用（[accesstoken如何获取？](#10013/第三步：获取access_token)）；<br>第三方应用需拥有「家校沟通」使用权限。<br>企业必须**完成验证**才可调用此接口，否则返回43009(企业需要验证)错误码。","request":{"auth":[{"name":"access_token","example":"ACCESS_TOKEN","type":1,"description":"","is_required":true,"default":""}],"body":[],"params":[],"formData":[]},"remainReq":[],"response":[{"status":"200","description":"","body":[{"name":"errcode","type":4,"description":"返回码","default":"","example":0,"items":{}},{"name":"errmsg","type":1,"description":"对返回码的文本描述内容","default":"","example":"ok","items":{}},{"name":"qrcode_big","type":1,"description":"1200px的大尺寸二维码","default":"","example":"http://p.qpic.cn/wwhead/XXXX","items":{}},{"name":"qrcode_middle","type":1,"description":"430px的中尺寸二维码","default":"","example":"http://p.qpic.cn/wwhead/XXXX","items":{}},{"name":"qrcode_thumb","type":1,"description":"258px的小尺寸二维码","default":"","example":"http://p.qpic.cn/wwhead/XXXX","items":{}}]}],"remainRes":[],"description":"学校可通过此接口获取「学校通知」二维码，家长可通过扫描此二维码关注「学校通知」并接收学校推送的消息。","status":2,"attention":"","cate_path":"服务端API-家校沟通-基础接口-获取「学校通知」二维码","isExampleError":false,"titleIndex":-1,"isInterface":true}